[
    {
        "controller": "Laravel\\Fortify\\Http\\Controllers\\AuthenticatedSessionController@create",
        "url": "login",
        "name": "login",
        "method": "GET"
    },
    {
        "controller": "Laravel\\Fortify\\Http\\Controllers\\PasswordResetLinkController@create",
        "url": "forgot-password",
        "name": "password.request",
        "method": "GET"
    },
    {
        "controller": "Laravel\\Fortify\\Http\\Controllers\\NewPasswordController@create",
        "url": "reset-password\/{token}",
        "name": "password.reset",
        "method": "GET"
    },
    {
        "controller": "Laravel\\Fortify\\Http\\Controllers\\RegisteredUserController@create",
        "url": "register",
        "name": "register",
        "method": "GET"
    },
    {
        "controller": "Laravel\\Fortify\\Http\\Controllers\\EmailVerificationPromptController@__invoke",
        "url": "email\/verify",
        "name": "verification.notice",
        "method": "GET"
    },
    {
        "controller": "Laravel\\Fortify\\Http\\Controllers\\VerifyEmailController@__invoke",
        "url": "email\/verify\/{id}\/{hash}",
        "name": "verification.verify",
        "method": "GET"
    },
    {
        "controller": "Laravel\\Fortify\\Http\\Controllers\\ConfirmablePasswordController@show",
        "url": "user\/confirm-password",
        "name": "password.confirm",
        "method": "GET"
    },
    {
        "controller": "Laravel\\Fortify\\Http\\Controllers\\ConfirmedPasswordStatusController@show",
        "url": "user\/confirmed-password-status",
        "name": "password.confirmation",
        "method": "GET"
    },
    {
        "controller": "Laravel\\Fortify\\Http\\Controllers\\TwoFactorAuthenticatedSessionController@create",
        "url": "two-factor-challenge",
        "name": "two-factor.login",
        "method": "GET"
    },
    {
        "controller": "Laravel\\Fortify\\Http\\Controllers\\TwoFactorQrCodeController@show",
        "url": "user\/two-factor-qr-code",
        "name": "two-factor.qr-code",
        "method": "GET"
    },
    {
        "controller": "Laravel\\Fortify\\Http\\Controllers\\RecoveryCodeController@index",
        "url": "user\/two-factor-recovery-codes",
        "name": "two-factor.recovery-codes",
        "method": "GET"
    },
    {
        "controller": "Laravel\\Jetstream\\Http\\Controllers\\Inertia\\UserProfileController@show",
        "url": "user\/profile",
        "name": "profile.show",
        "method": "GET"
    },
    {
        "controller": "Laravel\\Sanctum\\Http\\Controllers\\CsrfCookieController@show",
        "url": "sanctum\/csrf-cookie",
        "name": "generated::4qJniNlwupRZ65fJ",
        "method": "GET"
    },
    {
        "controller": "App\\Http\\Controllers\\API\\CategoryController@index",
        "url": "api\/category",
        "name": "category.index",
        "method": "GET"
    },
    {
        "controller": "App\\Http\\Controllers\\API\\CategoryController@create",
        "url": "api\/category\/create",
        "name": "category.create",
        "method": "GET"
    },
    {
        "controller": "App\\Http\\Controllers\\API\\CategoryController@show",
        "url": "api\/category\/{category}",
        "name": "category.show",
        "method": "GET"
    },
    {
        "controller": "App\\Http\\Controllers\\API\\CategoryController@edit",
        "url": "api\/category\/{category}\/edit",
        "name": "category.edit",
        "method": "GET"
    },
    {
        "controller": "App\\Http\\Controllers\\API\\UserController@get",
        "url": "api\/user\/{id}",
        "name": "user.",
        "method": "GET"
    },
    {
        "controller": "App\\Http\\Controllers\\Web\\Blog\\BlogController@index",
        "url": "\/",
        "name": "blog.",
        "method": "GET"
    },
    {
        "controller": "App\\Http\\Controllers\\Web\\Blog\\BlogController@tag",
        "url": "tag",
        "name": "blog.generated::mkemS98zJn6fSFzh",
        "method": "GET"
    },
    {
        "controller": "App\\Http\\Controllers\\Web\\Blog\\BlogController@example",
        "url": "example",
        "name": "blog.generated::JpwOv2aArLY50PR5",
        "method": "GET"
    },
    {
        "controller": "App\\Http\\Controllers\\Web\\Blog\\BlogController@verify",
        "url": "verify",
        "name": "blog.verify",
        "method": "GET"
    },
    {
        "controller": "App\\Http\\Controllers\\Web\\Blog\\PostController@index",
        "url": "post\/index",
        "name": "blog.post.",
        "method": "GET"
    },
    {
        "controller": "App\\Http\\Controllers\\Web\\Blog\\PostController@edit",
        "url": "post\/edit\/{id?}",
        "name": "blog.post.generated::mOzuLPWosHXr3SUc",
        "method": "GET"
    },
    {
        "controller": "App\\Http\\Controllers\\Web\\Blog\\MemberController@login",
        "url": "member\/login",
        "name": "blog.member.login",
        "method": "GET"
    },
    {
        "controller": "App\\Http\\Controllers\\Web\\Blog\\MemberController@register",
        "url": "member\/register",
        "name": "blog.member.register",
        "method": "GET"
    },
    {
        "controller": "App\\Http\\Controllers\\Web\\Blog\\MemberController@index",
        "url": "member\/index",
        "name": "blog.member.index",
        "method": "GET"
    },
    {
        "controller": "App\\Http\\Controllers\\Web\\Blog\\MemberController@changePassword",
        "url": "member\/change-password",
        "name": "blog.member.changePassword",
        "method": "GET"
    },
    {
        "controller": "App\\Http\\Controllers\\Web\\Blog\\MemberController@postList",
        "url": "member\/post-list",
        "name": "blog.member.postList",
        "method": "GET"
    },
    {
        "controller": "App\\Http\\Controllers\\Web\\Blog\\MemberController@reply",
        "url": "member\/reply",
        "name": "blog.member.reply",
        "method": "GET"
    },
    {
        "controller": "App\\Http\\Controllers\\Web\\Admin\\AdminController@roleSetting",
        "url": "admin\/permission-management\/role-setting",
        "name": "admin.permission-management.roleSetting",
        "method": "GET"
    },
    {
        "controller": "App\\Http\\Controllers\\Web\\Admin\\AdminController@userSetting",
        "url": "admin\/permission-management\/user-setting",
        "name": "admin.permission-management.userSetting",
        "method": "GET"
    },
    {
        "controller": "App\\Http\\Controllers\\Web\\Admin\\BlogController@post",
        "url": "admin\/blog\/post",
        "name": "admin.blog.post",
        "method": "GET"
    },
    {
        "controller": "App\\Http\\Controllers\\Web\\Admin\\BlogController@tag",
        "url": "admin\/blog\/tag",
        "name": "admin.blog.tag",
        "method": "GET"
    },
    {
        "controller": "App\\Http\\Controllers\\Web\\Admin\\BlogController@category",
        "url": "admin\/blog\/category",
        "name": "admin.blog.category",
        "method": "GET"
    },
    {
        "controller": "Closure",
        "url": "admin\/dashboard",
        "name": "admin.dashboard",
        "method": "GET"
    },
    {
        "controller": "Closure",
        "url": "admin",
        "name": "admin.",
        "method": "GET"
    },
    {
        "controller": "Laravel\\Fortify\\Http\\Controllers\\AuthenticatedSessionController@create",
        "url": "login",
        "name": "login",
        "method": "HEAD"
    },
    {
        "controller": "Laravel\\Fortify\\Http\\Controllers\\PasswordResetLinkController@create",
        "url": "forgot-password",
        "name": "password.request",
        "method": "HEAD"
    },
    {
        "controller": "Laravel\\Fortify\\Http\\Controllers\\NewPasswordController@create",
        "url": "reset-password\/{token}",
        "name": "password.reset",
        "method": "HEAD"
    },
    {
        "controller": "Laravel\\Fortify\\Http\\Controllers\\RegisteredUserController@create",
        "url": "register",
        "name": "register",
        "method": "HEAD"
    },
    {
        "controller": "Laravel\\Fortify\\Http\\Controllers\\EmailVerificationPromptController@__invoke",
        "url": "email\/verify",
        "name": "verification.notice",
        "method": "HEAD"
    },
    {
        "controller": "Laravel\\Fortify\\Http\\Controllers\\VerifyEmailController@__invoke",
        "url": "email\/verify\/{id}\/{hash}",
        "name": "verification.verify",
        "method": "HEAD"
    },
    {
        "controller": "Laravel\\Fortify\\Http\\Controllers\\ConfirmablePasswordController@show",
        "url": "user\/confirm-password",
        "name": "password.confirm",
        "method": "HEAD"
    },
    {
        "controller": "Laravel\\Fortify\\Http\\Controllers\\ConfirmedPasswordStatusController@show",
        "url": "user\/confirmed-password-status",
        "name": "password.confirmation",
        "method": "HEAD"
    },
    {
        "controller": "Laravel\\Fortify\\Http\\Controllers\\TwoFactorAuthenticatedSessionController@create",
        "url": "two-factor-challenge",
        "name": "two-factor.login",
        "method": "HEAD"
    },
    {
        "controller": "Laravel\\Fortify\\Http\\Controllers\\TwoFactorQrCodeController@show",
        "url": "user\/two-factor-qr-code",
        "name": "two-factor.qr-code",
        "method": "HEAD"
    },
    {
        "controller": "Laravel\\Fortify\\Http\\Controllers\\RecoveryCodeController@index",
        "url": "user\/two-factor-recovery-codes",
        "name": "two-factor.recovery-codes",
        "method": "HEAD"
    },
    {
        "controller": "Laravel\\Jetstream\\Http\\Controllers\\Inertia\\UserProfileController@show",
        "url": "user\/profile",
        "name": "profile.show",
        "method": "HEAD"
    },
    {
        "controller": "Laravel\\Sanctum\\Http\\Controllers\\CsrfCookieController@show",
        "url": "sanctum\/csrf-cookie",
        "name": "generated::4qJniNlwupRZ65fJ",
        "method": "HEAD"
    },
    {
        "controller": "App\\Http\\Controllers\\API\\CategoryController@index",
        "url": "api\/category",
        "name": "category.index",
        "method": "HEAD"
    },
    {
        "controller": "App\\Http\\Controllers\\API\\CategoryController@create",
        "url": "api\/category\/create",
        "name": "category.create",
        "method": "HEAD"
    },
    {
        "controller": "App\\Http\\Controllers\\API\\CategoryController@show",
        "url": "api\/category\/{category}",
        "name": "category.show",
        "method": "HEAD"
    },
    {
        "controller": "App\\Http\\Controllers\\API\\CategoryController@edit",
        "url": "api\/category\/{category}\/edit",
        "name": "category.edit",
        "method": "HEAD"
    },
    {
        "controller": "App\\Http\\Controllers\\API\\UserController@get",
        "url": "api\/user\/{id}",
        "name": "user.",
        "method": "HEAD"
    },
    {
        "controller": "App\\Http\\Controllers\\Web\\Blog\\BlogController@index",
        "url": "\/",
        "name": "blog.",
        "method": "HEAD"
    },
    {
        "controller": "App\\Http\\Controllers\\Web\\Blog\\BlogController@tag",
        "url": "tag",
        "name": "blog.generated::mkemS98zJn6fSFzh",
        "method": "HEAD"
    },
    {
        "controller": "App\\Http\\Controllers\\Web\\Blog\\BlogController@example",
        "url": "example",
        "name": "blog.generated::JpwOv2aArLY50PR5",
        "method": "HEAD"
    },
    {
        "controller": "App\\Http\\Controllers\\Web\\Blog\\BlogController@verify",
        "url": "verify",
        "name": "blog.verify",
        "method": "HEAD"
    },
    {
        "controller": "App\\Http\\Controllers\\Web\\Blog\\PostController@index",
        "url": "post\/index",
        "name": "blog.post.",
        "method": "HEAD"
    },
    {
        "controller": "App\\Http\\Controllers\\Web\\Blog\\PostController@edit",
        "url": "post\/edit\/{id?}",
        "name": "blog.post.generated::mOzuLPWosHXr3SUc",
        "method": "HEAD"
    },
    {
        "controller": "App\\Http\\Controllers\\Web\\Blog\\MemberController@login",
        "url": "member\/login",
        "name": "blog.member.login",
        "method": "HEAD"
    },
    {
        "controller": "App\\Http\\Controllers\\Web\\Blog\\MemberController@register",
        "url": "member\/register",
        "name": "blog.member.register",
        "method": "HEAD"
    },
    {
        "controller": "App\\Http\\Controllers\\Web\\Blog\\MemberController@index",
        "url": "member\/index",
        "name": "blog.member.index",
        "method": "HEAD"
    },
    {
        "controller": "App\\Http\\Controllers\\Web\\Blog\\MemberController@changePassword",
        "url": "member\/change-password",
        "name": "blog.member.changePassword",
        "method": "HEAD"
    },
    {
        "controller": "App\\Http\\Controllers\\Web\\Blog\\MemberController@postList",
        "url": "member\/post-list",
        "name": "blog.member.postList",
        "method": "HEAD"
    },
    {
        "controller": "App\\Http\\Controllers\\Web\\Blog\\MemberController@reply",
        "url": "member\/reply",
        "name": "blog.member.reply",
        "method": "HEAD"
    },
    {
        "controller": "App\\Http\\Controllers\\Web\\Admin\\AdminController@roleSetting",
        "url": "admin\/permission-management\/role-setting",
        "name": "admin.permission-management.roleSetting",
        "method": "HEAD"
    },
    {
        "controller": "App\\Http\\Controllers\\Web\\Admin\\AdminController@userSetting",
        "url": "admin\/permission-management\/user-setting",
        "name": "admin.permission-management.userSetting",
        "method": "HEAD"
    },
    {
        "controller": "App\\Http\\Controllers\\Web\\Admin\\BlogController@post",
        "url": "admin\/blog\/post",
        "name": "admin.blog.post",
        "method": "HEAD"
    },
    {
        "controller": "App\\Http\\Controllers\\Web\\Admin\\BlogController@tag",
        "url": "admin\/blog\/tag",
        "name": "admin.blog.tag",
        "method": "HEAD"
    },
    {
        "controller": "App\\Http\\Controllers\\Web\\Admin\\BlogController@category",
        "url": "admin\/blog\/category",
        "name": "admin.blog.category",
        "method": "HEAD"
    },
    {
        "controller": "Closure",
        "url": "admin\/dashboard",
        "name": "admin.dashboard",
        "method": "HEAD"
    },
    {
        "controller": "Closure",
        "url": "admin",
        "name": "admin.",
        "method": "HEAD"
    },
    {
        "controller": "Laravel\\Fortify\\Http\\Controllers\\AuthenticatedSessionController@store",
        "url": "login",
        "name": "generated::sWruMt2MKchJeuiG",
        "method": "POST"
    },
    {
        "controller": "Laravel\\Fortify\\Http\\Controllers\\AuthenticatedSessionController@destroy",
        "url": "logout",
        "name": "logout",
        "method": "POST"
    },
    {
        "controller": "Laravel\\Fortify\\Http\\Controllers\\PasswordResetLinkController@store",
        "url": "forgot-password",
        "name": "password.email",
        "method": "POST"
    },
    {
        "controller": "Laravel\\Fortify\\Http\\Controllers\\NewPasswordController@store",
        "url": "reset-password",
        "name": "password.update",
        "method": "POST"
    },
    {
        "controller": "Laravel\\Fortify\\Http\\Controllers\\RegisteredUserController@store",
        "url": "register",
        "name": "generated::YvkriP6WN6QhWGUK",
        "method": "POST"
    },
    {
        "controller": "Laravel\\Fortify\\Http\\Controllers\\EmailVerificationNotificationController@store",
        "url": "email\/verification-notification",
        "name": "verification.send",
        "method": "POST"
    },
    {
        "controller": "Laravel\\Fortify\\Http\\Controllers\\ConfirmablePasswordController@store",
        "url": "user\/confirm-password",
        "name": "generated::DEdwVvfnG7rIHpF1",
        "method": "POST"
    },
    {
        "controller": "Laravel\\Fortify\\Http\\Controllers\\TwoFactorAuthenticatedSessionController@store",
        "url": "two-factor-challenge",
        "name": "generated::gVqa8Qk99himuaSq",
        "method": "POST"
    },
    {
        "controller": "Laravel\\Fortify\\Http\\Controllers\\TwoFactorAuthenticationController@store",
        "url": "user\/two-factor-authentication",
        "name": "two-factor.enable",
        "method": "POST"
    },
    {
        "controller": "Laravel\\Fortify\\Http\\Controllers\\RecoveryCodeController@store",
        "url": "user\/two-factor-recovery-codes",
        "name": "generated::OpYDBX89mGv0LdGJ",
        "method": "POST"
    },
    {
        "controller": "App\\Http\\Controllers\\API\\PostController@store",
        "url": "api\/post",
        "name": "generated::2HgJ1hcmdjRgOZt9",
        "method": "POST"
    },
    {
        "controller": "App\\Http\\Controllers\\API\\CategoryController@store",
        "url": "api\/category",
        "name": "category.store",
        "method": "POST"
    },
    {
        "controller": "App\\Http\\Controllers\\API\\UserController@store",
        "url": "api\/user",
        "name": "user.generated::bQxzlTVgZ2xsNaVa",
        "method": "POST"
    },
    {
        "controller": "Laravel\\Fortify\\Http\\Controllers\\ProfileInformationController@update",
        "url": "user\/profile-information",
        "name": "user-profile-information.update",
        "method": "PUT"
    },
    {
        "controller": "Laravel\\Fortify\\Http\\Controllers\\PasswordController@update",
        "url": "user\/password",
        "name": "user-password.update",
        "method": "PUT"
    },
    {
        "controller": "App\\Http\\Controllers\\API\\PostController@update",
        "url": "api\/post\/{id}",
        "name": "generated::YAMoAw3zA33USSu4",
        "method": "PUT"
    },
    {
        "controller": "App\\Http\\Controllers\\API\\CategoryController@update",
        "url": "api\/category\/{category}",
        "name": "category.update",
        "method": "PUT"
    },
    {
        "controller": "App\\Http\\Controllers\\API\\UserController@update",
        "url": "api\/user\/{id}",
        "name": "user.generated::YUuEqERPc3T6hDt4",
        "method": "PUT"
    },
    {
        "controller": "Laravel\\Fortify\\Http\\Controllers\\TwoFactorAuthenticationController@destroy",
        "url": "user\/two-factor-authentication",
        "name": "two-factor.disable",
        "method": "DELETE"
    },
    {
        "controller": "Laravel\\Jetstream\\Http\\Controllers\\Inertia\\OtherBrowserSessionsController@destroy",
        "url": "user\/other-browser-sessions",
        "name": "other-browser-sessions.destroy",
        "method": "DELETE"
    },
    {
        "controller": "Laravel\\Jetstream\\Http\\Controllers\\Inertia\\ProfilePhotoController@destroy",
        "url": "user\/profile-photo",
        "name": "current-user-photo.destroy",
        "method": "DELETE"
    },
    {
        "controller": "Laravel\\Jetstream\\Http\\Controllers\\Inertia\\CurrentUserController@destroy",
        "url": "user",
        "name": "current-user.destroy",
        "method": "DELETE"
    },
    {
        "controller": "App\\Http\\Controllers\\API\\PostController@delete",
        "url": "api\/post\/{id}",
        "name": "generated::MhMisoLk4tlXjMZz",
        "method": "DELETE"
    },
    {
        "controller": "App\\Http\\Controllers\\API\\CategoryController@destroy",
        "url": "api\/category\/{category}",
        "name": "category.destroy",
        "method": "DELETE"
    },
    {
        "controller": "App\\Http\\Controllers\\API\\CategoryController@update",
        "url": "api\/category\/{category}",
        "name": "category.update",
        "method": "PATCH"
    }
]